engineer/__init__.py
engineer/_version.py
engineer/cache.py
engineer/conf.py
engineer/emma.py
engineer/engine.py
engineer/enums.py
engineer/exceptions.py
engineer/filters.py
engineer/finders.py
engineer/loaders.py
engineer/log.py
engineer/models.py
engineer/processors.py
engineer/themes.py
engineer/util.py
engineer/contrib/__init__.py
engineer/devtools/__init__.py
engineer/devtools/theme_tools.py
engineer/docs_source/bundled_plugins.rst
engineer/docs_source/changelog.rst
engineer/docs_source/cmdline.rst
engineer/docs_source/compatibility.rst
engineer/docs_source/conf.py
engineer/docs_source/deployment.rst
engineer/docs_source/emma.rst
engineer/docs_source/faq.rst
engineer/docs_source/index.rst
engineer/docs_source/installation.rst
engineer/docs_source/intro.rst
engineer/docs_source/navigation.rst
engineer/docs_source/posts.rst
engineer/docs_source/settings.rst
engineer/docs_source/templates.rst
engineer/docs_source/themes.rst
engineer/docs_source/tidbits.rst
engineer/docs_source/tutorial.rst
engineer/docs_source/upgrade.rst
engineer/docs_source/api/engineer.conf.rst
engineer/docs_source/api/engineer.engine.rst
engineer/docs_source/api/engineer.enums.rst
engineer/docs_source/api/engineer.finders.rst
engineer/docs_source/api/engineer.models.rst
engineer/docs_source/api/engineer.themes.rst
engineer/docs_source/deploying/azure.rst
engineer/docs_source/dev/macros.rst
engineer/docs_source/dev/pipeline.rst
engineer/docs_source/dev/plugins.rst
engineer/docs_source/dev/template_contexts.rst
engineer/docs_source/dev/theme_creation.rst
engineer/docs_source/themes/dark_rainbow.rst
engineer/docs_source/themes/oleb.rst
engineer/lib/__init__.py
engineer/lib/ansistrm.py
engineer/lib/jinja2htmlcompress.py
engineer/lib/less.js-windows/LICENSE
engineer/lib/less.js-windows/README.md
engineer/lib/less.js-windows/lessc-watch.cmd
engineer/lib/less.js-windows/lessc.cmd
engineer/lib/less.js-windows/bin/Node LICENSE.txt
engineer-0.5.2.dist-info/DESCRIPTION.rst
engineer-0.5.2.dist-info/METADATA
engineer-0.5.2.dist-info/RECORD
engineer-0.5.2.dist-info/WHEEL
engineer-0.5.2.dist-info/entry_points.txt
engineer-0.5.2.dist-info/metadata.json
engineer-0.5.2.dist-info/top_level.txt
engineer-0.5.2.dist-info/zip-safe
