Metadata-Version: 2.0
Name: engineer
Version: 0.5.2
Summary: A static website generator.
Home-page: http://github.com/tylerbutler/engineer
Author: Tyler Butler
Author-email: tyler@tylerbutler.com
License: MIT
Platform: any
Requires-Dist: appdirs (==1.4.3)
Requires-Dist: bottle (==0.12.13)
Requires-Dist: brownie (==0.5.1)
Requires-Dist: cssmin (==0.2.0)
Requires-Dist: feedgenerator (==1.9)
Requires-Dist: flufl.enum (==4.1.1)
Requires-Dist: html5lib (==0.90)
Requires-Dist: humanize (==0.5.1)
Requires-Dist: Jinja2 (==2.9.6)
Requires-Dist: lpjsmin (==0.5)
Requires-Dist: markdown (==2.6.8)
Requires-Dist: path.py (<10.0,>=9.0)
Requires-Dist: propane (>=0.2.1)
Requires-Dist: pygments (==2.2.0)
Requires-Dist: python-dateutil (==2.6.0)
Requires-Dist: pytz (>=2017.2)
Requires-Dist: pyYAML (==3.12)
Requires-Dist: times (==0.6.2)
Requires-Dist: translitcodec (==0.4.0)
Requires-Dist: typogrify-engineer (>=2.0.0)
Provides-Extra: dev
Requires-Dist: argh; extra == 'dev'
Requires-Dist: clint; extra == 'dev'
